pheval_amelie/__init__.py
pheval_amelie/cli.py
pheval_amelie/constants.py
pheval_amelie/main.py
pheval_amelie/post_process/__init__.py
pheval_amelie/post_process/post_process.py
pheval_amelie/post_process/post_process_results_format.py
pheval_amelie/prepare/__init__.py
pheval_amelie/run/__init__.py
pheval_amelie/run/prepare_requests.py
pheval_amelie/run/run.py
pheval_amelie/runner.py
pheval_amelie-0.1.0.dist-info/LICENSE
pheval_amelie-0.1.0.dist-info/METADATA
pheval_amelie-0.1.0.dist-info/WHEEL
pheval_amelie-0.1.0.dist-info/entry_points.txt
pheval_amelie-0.1.0.dist-info/RECORD
