Metadata-Version: 2.1
Name: pheval_amelie
Version: 0.1.0
Summary: pheval_amelie
License: Apache Software License 2.0
Author: Yasemin Bridges
Author-email: y.bridges@qmul.ac.uk
Requires-Python: >=3.9,<4.0
Classifier: License :: Other/Proprietary License
Classifier: Programming Language :: Python :: 3
Classifier: Programming Language :: Python :: 3.9
Classifier: Programming Language :: Python :: 3.10
Classifier: Programming Language :: Python :: 3.11
Classifier: Programming Language :: Python :: 3.12
Classifier: Programming Language :: Python :: 3.13
Requires-Dist: click
Requires-Dist: importlib-metadata (>=8.2.0)
Requires-Dist: pheval (>=0.4.0,<0.5.0)
